functr/__init__.py
functr/callbacks.py
functr/inputs.py
functr/utils.py
functr/layers/__init__.py
functr/layers/activation.py
functr/layers/core.py
functr/layers/interaction.py
functr/layers/sequence.py
functr/layers/utils.py
functr/models/__init__.py
functr/models/afm.py
functr/models/afn.py
functr/models/autoint.py
functr/models/basemodel.py
functr/models/ccpm.py
functr/models/dcn.py
functr/models/dcnmix.py
functr/models/deepfm.py
functr/models/dien.py
functr/models/difm.py
functr/models/din.py
functr/models/fibinet.py
functr/models/ifm.py
functr/models/mlr.py
functr/models/nfm.py
functr/models/onn.py
functr/models/pnn.py
functr/models/wdl.py
functr/models/xdeepfm.py
functr/models/multitask/__init__.py
functr/models/multitask/esmm.py
functr/models/multitask/mmoe.py
functr/models/multitask/ple.py
functr/models/multitask/sharedbottom.py
functr-1.0.8.dist-info/METADATA
functr-1.0.8.dist-info/WHEEL
functr-1.0.8.dist-info/top_level.txt
functr-1.0.8.dist-info/RECORD
