Metadata-Version: 2.1
Name: functr
Version: 1.0.8
Summary: Add your description here
Requires-Python: >=3.9
Requires-Dist: scikit-learn >=1.5.2
Requires-Dist: torch >=2.5.0
Requires-Dist: tqdm >=4.66.5
